pnt3/.DS_Store
pnt3/__init__.py
pnt3/src/.DS_Store
pnt3/src/calc_similarity.py
pnt3/src/canonical.py
pnt3/src/cfg_pnt3.py
pnt3/src/create_joint_table.py
pnt3/src/create_table.py
pnt3/src/draw_canonical.py
pnt3/src/draw_image_warp.py
pnt3/src/draw_magn.py
pnt3/src/draw_peaks.py
pnt3/src/draw_result.py
pnt3/src/draw_similarity_map.py
pnt3/src/draw_utils.py
pnt3/src/get_angle.py
pnt3/src/get_peaks.py
pnt3/src/get_similarity.py
pnt3/src/magnitude.py
pnt3/src/utils.py
pnt3/src/utils_list.py
pnt3-1.0.3.dist-info/METADATA
pnt3-1.0.3.dist-info/WHEEL
pnt3-1.0.3.dist-info/RECORD
